cle_sh-0.1.0.dist-info/licenses/LICENSE
clesh/__init__.py
clesh/clesh.py
cle_sh-0.1.0.dist-info/METADATA
cle_sh-0.1.0.dist-info/WHEEL
cle_sh-0.1.0.dist-info/top_level.txt
cle_sh-0.1.0.dist-info/RECORD
