Metadata-Version: 2.4
Name: cle-sh
Version: 0.1.0
Summary: CLE-SH: Comprehensive Literal Explanation package for SHapley values by statistical validity (arXiv:2409.12578)
Author: CLE-SH Contributors
License-Expression: MIT
Project-URL: Homepage, https://github.com/rrtjr/cle-sh
Project-URL: Repository, https://github.com/rrtjr/cle-sh
Project-URL: Documentation, https://github.com/rrtjr/cle-sh#readme
Project-URL: Bug Tracker, https://github.com/rrtjr/cle-sh/issues
Keywords: machine-learning,explainable-ai,shap,statistics,interpretability
Classifier: Development Status :: 4 - Beta
Classifier: Intended Audience :: Developers
Classifier: Intended Audience :: Science/Research
Classifier: Operating System :: OS Independent
Classifier: Programming Language :: Python :: 3
Classifier: Programming Language :: Python :: 3.9
Classifier: Programming Language :: Python :: 3.10
Classifier: Programming Language :: Python :: 3.11
Classifier: Programming Language :: Python :: 3.12
Classifier: Topic :: Scientific/Engineering :: Artificial Intelligence
Classifier: Topic :: Scientific/Engineering :: Information Analysis
Requires-Python: >=3.9
License-File: LICENSE
Requires-Dist: numpy>=1.21.0
Requires-Dist: pandas>=1.3.0
Requires-Dist: scipy>=1.7.0
Requires-Dist: statsmodels>=0.13.0
Requires-Dist: shap>=0.41.0
Requires-Dist: loguru>=0.6.0
Requires-Dist: scikit-learn>=1.5.0
Provides-Extra: viz
Requires-Dist: matplotlib>=3.7.0; extra == "viz"
Requires-Dist: seaborn>=0.11.0; extra == "viz"
Provides-Extra: examples
Requires-Dist: scikit-learn>=1.5.0; extra == "examples"
Provides-Extra: dev
Requires-Dist: pytest>=6.0; extra == "dev"
Requires-Dist: pytest-cov>=3.0; extra == "dev"
Requires-Dist: ruff>=0.4.8; extra == "dev"
Requires-Dist: pre-commit>=3.5.0; extra == "dev"
Requires-Dist: scikit-learn>=1.5.0; extra == "dev"
Provides-Extra: test
Requires-Dist: pytest>=6.0; extra == "test"
Requires-Dist: pytest-cov>=3.0; extra == "test"
Requires-Dist: scikit-learn>=1.5.0; extra == "test"
Provides-Extra: all
Requires-Dist: matplotlib>=3.7.0; extra == "all"
Requires-Dist: seaborn>=0.11.0; extra == "all"
Requires-Dist: scikit-learn>=1.5.0; extra == "all"
Dynamic: license-file
